dollar_templates/__init__.py
dollar_templates/parser.py
dollar_templates/syntax.py
dollar_templates/tokenizer.py
dollar_templates-1.0.1.dist-info/METADATA
dollar_templates-1.0.1.dist-info/WHEEL
dollar_templates-1.0.1.dist-info/top_level.txt
dollar_templates-1.0.1.dist-info/RECORD
