Metadata-Version: 2.1
Name: dollar-templates
Version: 1.0.1
Summary: Pandoc style dollar templates for python
Home-page: https://github.com/seifferth/dollar_templates
Author: Frank Seifferth
Author-email: frankseifferth@posteo.net
Classifier: Programming Language :: Python :: 3
Classifier: License :: OSI Approved :: GNU General Public License v3 or later (GPLv3+)
Classifier: Operating System :: OS Independent
Requires-Python: >=3.9
